tempfile312/__init__.py
tempfile312/__init__.pyi
tempfile312/py.typed
tempfile312-1.0.1.dist-info/LICENSE
tempfile312-1.0.1.dist-info/METADATA
tempfile312-1.0.1.dist-info/WHEEL
tempfile312-1.0.1.dist-info/top_level.txt
tempfile312-1.0.1.dist-info/RECORD
