Metadata-Version: 2.1
Name: tempfile312
Version: 1.0.1
Summary: Backport of Python 3.12's tempfile library for Python 3.8+
Author-email: Red Balloon Security <ofrak@redballoonsecurity.com>
Project-URL: Homepage, https://github.com/rbs-forks/tempfile312
Project-URL: Source, https://github.com/rbs-forks/tempfile312
Project-URL: Documentation, https://docs.python.org/3.12/library/tempfile.html
Keywords: tempfile,backport
Classifier: Programming Language :: Python :: 3
Classifier: Programming Language :: Python :: 3.8
Classifier: Programming Language :: Python :: 3.9
Classifier: Programming Language :: Python :: 3.10
Classifier: Programming Language :: Python :: 3.11
Classifier: Programming Language :: Python :: 3.12
Classifier: License :: OSI Approved :: Python Software Foundation License
Requires-Python: >=3.8
License-File: LICENSE
